ccxtools/__init__.py
ccxtools/binance.py
ccxtools/binance_coin.py
ccxtools/binance_usdt.py
ccxtools/bingx.py
ccxtools/bitget.py
ccxtools/bithumb.py
ccxtools/bybit.py
ccxtools/huobi.py
ccxtools/okx.py
ccxtools/tools.py
ccxtools/upbit.py
ccxtools/base/CcxtExchange.py
ccxtools/base/CcxtFutureExchange.py
ccxtools/base/Exchange.py
ccxtools/base/FutureExchange.py
ccxtools/base/__init__.py
ccxtools/base/ccxt_fetch_mixin.py
ccxtools/ccserver/__init__.py
ccxtools/ccserver/server_fetcher.py
ccxtools-0.0.140.dist-info/METADATA
ccxtools-0.0.140.dist-info/WHEEL
ccxtools-0.0.140.dist-info/top_level.txt
ccxtools-0.0.140.dist-info/RECORD
