Metadata-Version: 2.1
Name: ccxtools
Version: 0.0.140
Summary: ccxtools
Home-page: https://github.com/WoosubLeee/ccxtools
Author: Woosub Lee
Author-email: zbxv1423@naver.com
Classifier: Programming Language :: Python :: 3
Requires-Python: >=3.6
Requires-Dist: ccxt ==4.2.86
Requires-Dist: beautifulsoup4 ==4.12.2
Requires-Dist: python-decouple ==3.6
Requires-Dist: selenium ==4.15.2
